{
    "os": "Linux-4.15.0-162-generic-x86_64-with-glibc2.27",
    "python": "3.9.13",
    "heartbeatAt": "2023-01-16T10:59:17.014184",
    "startedAt": "2023-01-16T10:59:15.620322",
    "docker": null,
    "cuda": null,
    "args": [
        "--train_task",
        "scratch",
        "--train_src",
        "eicu",
        "--structure",
        "hi",
        "--emb_type",
        "textbase",
        "--feature",
        "whole",
        "--pred_model",
        "eventaggregator",
        "--n_layers",
        "2",
        "--max_seq_len",
        "256",
        "--batch_size",
        "16",
        "--world_size",
        "1",
        "--criterion",
        "prediction",
        "--valid_subset",
        "valid,test",
        "--wandb"
    ],
    "state": "running",
    "program": "/nfs_edlab/ghhur/github/UniHPF/run/scratch/../../main.py",
    "codePath": "main.py",
    "git": {
        "remote": "https://github.com/hoon9405/UniHPF.git",
        "commit": "df6c5d000990f572afb34a4dc50995211b642bda"
    },
    "email": "hkhxoxo@gmail.com",
    "root": "/nfs_edlab/ghhur/github/UniHPF",
    "host": "gpuserver2",
    "username": "ghhur",
    "executable": "/home/ghhur/.conda/envs/fedpxn/bin/python3",
    "cpu_count": 128,
    "cpu_count_logical": 128,
    "cpu_freq": {
        "current": 1586.1863906250012,
        "min": 1500.0,
        "max": 2000.0
    },
    "cpu_freq_per_core": [
        {
            "current": 1499.797,
            "min": 1500.0,
            "max": 2000.0
        },
        {
            "current": 1497.695,
            "min": 1500.0,
            "max": 2000.0
        },
        {
            "current": 1498.392,
            "min": 1500.0,
            "max": 2000.0
        },
        {
            "current": 1499.057,
            "min": 1500.0,
            "max": 2000.0
        },
        {
            "current": 1498.666,
            "min": 1500.0,
            "max": 2000.0
        },
        {
            "current": 1498.86,
            "min": 1500.0,
            "max": 2000.0
        },
        {
            "current": 1497.859,
            "min": 1500.0,
            "max": 2000.0
        },
        {
            "current": 1499.852,
            "min": 1500.0,
            "max": 2000.0
        },
        {
            "current": 1499.124,
            "min": 1500.0,
            "max": 2000.0
        },
        {
            "current": 1499.907,
            "min": 1500.0,
            "max": 2000.0
        },
        {
            "current": 1499.383,
            "min": 1500.0,
            "max": 2000.0
        },
        {
            "current": 1497.336,
            "min": 1500.0,
            "max": 2000.0
        },
        {
            "current": 1498.151,
            "min": 1500.0,
            "max": 2000.0
        },
        {
            "current": 1499.873,
            "min": 1500.0,
            "max": 2000.0
        },
        {
            "current": 1498.158,
            "min": 1500.0,
            "max": 2000.0
        },
        {
            "current": 1499.994,
            "min": 1500.0,
            "max": 2000.0
        },
        {
            "current": 1497.93,
            "min": 1500.0,
            "max": 2000.0
        },
        {
            "current": 1499.055,
            "min": 1500.0,
            "max": 2000.0
        },
        {
            "current": 1499.962,
            "min": 1500.0,
            "max": 2000.0
        },
        {
            "current": 1497.799,
            "min": 1500.0,
            "max": 2000.0
        },
        {
            "current": 1498.113,
            "min": 1500.0,
            "max": 2000.0
        },
        {
            "current": 1499.984,
            "min": 1500.0,
            "max": 2000.0
        },
        {
            "current": 1498.828,
            "min": 1500.0,
            "max": 2000.0
        },
        {
            "current": 1499.129,
            "min": 1500.0,
            "max": 2000.0
        },
        {
            "current": 1498.717,
            "min": 1500.0,
            "max": 2000.0
        },
        {
            "current": 1498.536,
            "min": 1500.0,
            "max": 2000.0
        },
        {
            "current": 1498.177,
            "min": 1500.0,
            "max": 2000.0
        },
        {
            "current": 1500.081,
            "min": 1500.0,
            "max": 2000.0
        },
        {
            "current": 1498.018,
            "min": 1500.0,
            "max": 2000.0
        },
        {
            "current": 1499.994,
            "min": 1500.0,
            "max": 2000.0
        },
        {
            "current": 1498.601,
            "min": 1500.0,
            "max": 2000.0
        },
        {
            "current": 1497.105,
            "min": 1500.0,
            "max": 2000.0
        },
        {
            "current": 1500.253,
            "min": 1500.0,
            "max": 2000.0
        },
        {
            "current": 1499.373,
            "min": 1500.0,
            "max": 2000.0
        },
        {
            "current": 1497.976,
            "min": 1500.0,
            "max": 2000.0
        },
        {
            "current": 1497.824,
            "min": 1500.0,
            "max": 2000.0
        },
        {
            "current": 1497.967,
            "min": 1500.0,
            "max": 2000.0
        },
        {
            "current": 1499.641,
            "min": 1500.0,
            "max": 2000.0
        },
        {
            "current": 1499.804,
            "min": 1500.0,
            "max": 2000.0
        },
        {
            "current": 1499.819,
            "min": 1500.0,
            "max": 2000.0
        },
        {
            "current": 1498.525,
            "min": 1500.0,
            "max": 2000.0
        },
        {
            "current": 1499.297,
            "min": 1500.0,
            "max": 2000.0
        },
        {
            "current": 1499.64,
            "min": 1500.0,
            "max": 2000.0
        },
        {
            "current": 1382.237,
            "min": 1500.0,
            "max": 2000.0
        },
        {
            "current": 1443.358,
            "min": 1500.0,
            "max": 2000.0
        },
        {
            "current": 1497.389,
            "min": 1500.0,
            "max": 2000.0
        },
        {
            "current": 1497.694,
            "min": 1500.0,
            "max": 2000.0
        },
        {
            "current": 1498.782,
            "min": 1500.0,
            "max": 2000.0
        },
        {
            "current": 1497.318,
            "min": 1500.0,
            "max": 2000.0
        },
        {
            "current": 1498.632,
            "min": 1500.0,
            "max": 2000.0
        },
        {
            "current": 1498.162,
            "min": 1500.0,
            "max": 2000.0
        },
        {
            "current": 1499.316,
            "min": 1500.0,
            "max": 2000.0
        },
        {
            "current": 1499.57,
            "min": 1500.0,
            "max": 2000.0
        },
        {
            "current": 1499.852,
            "min": 1500.0,
            "max": 2000.0
        },
        {
            "current": 1497.937,
            "min": 1500.0,
            "max": 2000.0
        },
        {
            "current": 1498.118,
            "min": 1500.0,
            "max": 2000.0
        },
        {
            "current": 1497.291,
            "min": 1500.0,
            "max": 2000.0
        },
        {
            "current": 1499.313,
            "min": 1500.0,
            "max": 2000.0
        },
        {
            "current": 1498.29,
            "min": 1500.0,
            "max": 2000.0
        },
        {
            "current": 1498.46,
            "min": 1500.0,
            "max": 2000.0
        },
        {
            "current": 1497.625,
            "min": 1500.0,
            "max": 2000.0
        },
        {
            "current": 1500.165,
            "min": 1500.0,
            "max": 2000.0
        },
        {
            "current": 1498.031,
            "min": 1500.0,
            "max": 2000.0
        },
        {
            "current": 1498.306,
            "min": 1500.0,
            "max": 2000.0
        },
        {
            "current": 1497.487,
            "min": 1500.0,
            "max": 2000.0
        },
        {
            "current": 1499.37,
            "min": 1500.0,
            "max": 2000.0
        },
        {
            "current": 1497.625,
            "min": 1500.0,
            "max": 2000.0
        },
        {
            "current": 1497.887,
            "min": 1500.0,
            "max": 2000.0
        },
        {
            "current": 3345.511,
            "min": 1500.0,
            "max": 2000.0
        },
        {
            "current": 1486.323,
            "min": 1500.0,
            "max": 2000.0
        },
        {
            "current": 1486.175,
            "min": 1500.0,
            "max": 2000.0
        },
        {
            "current": 1488.53,
            "min": 1500.0,
            "max": 2000.0
        },
        {
            "current": 1489.086,
            "min": 1500.0,
            "max": 2000.0
        },
        {
            "current": 1488.405,
            "min": 1500.0,
            "max": 2000.0
        },
        {
            "current": 1486.15,
            "min": 1500.0,
            "max": 2000.0
        },
        {
            "current": 3314.093,
            "min": 1500.0,
            "max": 2000.0
        },
        {
            "current": 1487.159,
            "min": 1500.0,
            "max": 2000.0
        },
        {
            "current": 1485.774,
            "min": 1500.0,
            "max": 2000.0
        },
        {
            "current": 1487.831,
            "min": 1500.0,
            "max": 2000.0
        },
        {
            "current": 3344.917,
            "min": 1500.0,
            "max": 2000.0
        },
        {
            "current": 1560.125,
            "min": 1500.0,
            "max": 2000.0
        },
        {
            "current": 1498.835,
            "min": 1500.0,
            "max": 2000.0
        },
        {
            "current": 1499.47,
            "min": 1500.0,
            "max": 2000.0
        },
        {
            "current": 1498.255,
            "min": 1500.0,
            "max": 2000.0
        },
        {
            "current": 1499.483,
            "min": 1500.0,
            "max": 2000.0
        },
        {
            "current": 1498.206,
            "min": 1500.0,
            "max": 2000.0
        },
        {
            "current": 1498.979,
            "min": 1500.0,
            "max": 2000.0
        },
        {
            "current": 1499.094,
            "min": 1500.0,
            "max": 2000.0
        },
        {
            "current": 1499.159,
            "min": 1500.0,
            "max": 2000.0
        },
        {
            "current": 1496.722,
            "min": 1500.0,
            "max": 2000.0
        },
        {
            "current": 1498.584,
            "min": 1500.0,
            "max": 2000.0
        },
        {
            "current": 1500.443,
            "min": 1500.0,
            "max": 2000.0
        },
        {
            "current": 1498.07,
            "min": 1500.0,
            "max": 2000.0
        },
        {
            "current": 1496.428,
            "min": 1500.0,
            "max": 2000.0
        },
        {
            "current": 1499.555,
            "min": 1500.0,
            "max": 2000.0
        },
        {
            "current": 1498.462,
            "min": 1500.0,
            "max": 2000.0
        },
        {
            "current": 3353.728,
            "min": 1500.0,
            "max": 2000.0
        },
        {
            "current": 1488.24,
            "min": 1500.0,
            "max": 2000.0
        },
        {
            "current": 1487.23,
            "min": 1500.0,
            "max": 2000.0
        },
        {
            "current": 1486.444,
            "min": 1500.0,
            "max": 2000.0
        },
        {
            "current": 1497.869,
            "min": 1500.0,
            "max": 2000.0
        },
        {
            "current": 1497.308,
            "min": 1500.0,
            "max": 2000.0
        },
        {
            "current": 1499.658,
            "min": 1500.0,
            "max": 2000.0
        },
        {
            "current": 1497.854,
            "min": 1500.0,
            "max": 2000.0
        },
        {
            "current": 1498.55,
            "min": 1500.0,
            "max": 2000.0
        },
        {
            "current": 1499.817,
            "min": 1500.0,
            "max": 2000.0
        },
        {
            "current": 1498.225,
            "min": 1500.0,
            "max": 2000.0
        },
        {
            "current": 1496.619,
            "min": 1500.0,
            "max": 2000.0
        },
        {
            "current": 1498.533,
            "min": 1500.0,
            "max": 2000.0
        },
        {
            "current": 1499.546,
            "min": 1500.0,
            "max": 2000.0
        },
        {
            "current": 1497.921,
            "min": 1500.0,
            "max": 2000.0
        },
        {
            "current": 1497.682,
            "min": 1500.0,
            "max": 2000.0
        },
        {
            "current": 1487.836,
            "min": 1500.0,
            "max": 2000.0
        },
        {
            "current": 3320.124,
            "min": 1500.0,
            "max": 2000.0
        },
        {
            "current": 1485.582,
            "min": 1500.0,
            "max": 2000.0
        },
        {
            "current": 1486.654,
            "min": 1500.0,
            "max": 2000.0
        },
        {
            "current": 1498.868,
            "min": 1500.0,
            "max": 2000.0
        },
        {
            "current": 1497.923,
            "min": 1500.0,
            "max": 2000.0
        },
        {
            "current": 1498.095,
            "min": 1500.0,
            "max": 2000.0
        },
        {
            "current": 1498.398,
            "min": 1500.0,
            "max": 2000.0
        },
        {
            "current": 1499.739,
            "min": 1500.0,
            "max": 2000.0
        },
        {
            "current": 1498.293,
            "min": 1500.0,
            "max": 2000.0
        },
        {
            "current": 1498.213,
            "min": 1500.0,
            "max": 2000.0
        },
        {
            "current": 1498.92,
            "min": 1500.0,
            "max": 2000.0
        },
        {
            "current": 3331.854,
            "min": 1500.0,
            "max": 2000.0
        },
        {
            "current": 3353.534,
            "min": 1500.0,
            "max": 2000.0
        },
        {
            "current": 1487.19,
            "min": 1500.0,
            "max": 2000.0
        },
        {
            "current": 1487.771,
            "min": 1500.0,
            "max": 2000.0
        }
    ],
    "disk": {
        "total": 1724.4805030822754,
        "used": 1337.8370094299316
    },
    "gpu": "NVIDIA RTX A6000",
    "gpu_count": 8,
    "gpu_devices": [
        {
            "name": "NVIDIA RTX A6000",
            "memory_total": 51050315776
        },
        {
            "name": "NVIDIA RTX A6000",
            "memory_total": 51050315776
        },
        {
            "name": "NVIDIA RTX A6000",
            "memory_total": 51050315776
        },
        {
            "name": "NVIDIA RTX A6000",
            "memory_total": 51050315776
        },
        {
            "name": "NVIDIA RTX A6000",
            "memory_total": 51050315776
        },
        {
            "name": "NVIDIA RTX A6000",
            "memory_total": 51050315776
        },
        {
            "name": "NVIDIA RTX A6000",
            "memory_total": 51050315776
        },
        {
            "name": "NVIDIA RTX A6000",
            "memory_total": 51050315776
        }
    ],
    "memory": {
        "total": 1007.7555732727051
    }
}
